py_vor/QueryRunner.py
py_vor/__init__.py
py_vor/tools/CursorFactory.py
py_vor/tools/ResultsFormatter.py
py_vor/tools/__init__.py
py_vor/tools/download_from_s3.py
py_vor/tools/get_secret.py
py_vor/tools/upload_to_s3.py
py_vor/tools/write_to_csv.py
py_vor-0.0.9.dist-info/METADATA
py_vor-0.0.9.dist-info/RECORD
py_vor-0.0.9.dist-info/WHEEL
py_vor-0.0.9.dist-info/top_level.txt
