Metadata-Version: 2.1
Name: py-vor
Version: 0.0.9
Summary: BI automation utilities.
Home-page: https://github.com/ksco92/py_vor
Author: Rodrigo Carvajal
Author-email: rodrigocf_92@hotmail.com
License: MIT
Platform: UNKNOWN
Requires-Dist: boto3
Requires-Dist: pandas
Requires-Dist: pymssql
Requires-Dist: pymysql
Requires-Dist: pg8000
